supplies/__init__.py
supplies/reptiles/__init__.py
supplies/reptiles/cookies.py
supplies/reptiles/useragents.py
supplies-0.10.2.dist-info/LICENSE
supplies-0.10.2.dist-info/METADATA
supplies-0.10.2.dist-info/WHEEL
supplies-0.10.2.dist-info/top_level.txt
supplies-0.10.2.dist-info/RECORD
