Metadata-Version: 2.1
Name: supplies
Version: 0.10.2
Summary: Parameters supply.
Author-email: "左易晗(from china)" <19156653620@163.com>
Keywords: suuplies,supply,parmas,crawler
Classifier: Programming Language :: Python :: 3
Classifier: License :: OSI Approved :: MIT License
Classifier: Operating System :: OS Independent
Requires-Python: >=3.1
License-File: LICENSE
Requires-Dist: requests >=2.31.0
